{
  "@context": "https://doi.org/10.5063/schema/codemeta-2.0",
  "@type": "SoftwareSourceCode",
  "identifier": "nomisdata",
  "description": "Interface to the 'Nomis' database (<https://www.nomisweb.co.uk>), a comprehensive resource of United Kingdom labour market statistics provided by the Office for National Statistics (ONS). Facilitates programmatic access to census data, labour force surveys, benefit statistics, and socioeconomic indicators through a modern HTTP client with intelligent caching, automatic query pagination, and tidy data principles. Includes spatial data integration, interactive helpers, and visualization utilities. Independent implementation unaffiliated with ONS or Durham University.",
  "name": "nomisdata: Access 'Nomis' UK Labour Market Data and Statistics",
  "codeRepository": "https://github.com/cherylisabella/nomisdata",
  "issueTracker": "https://github.com/cherylisabella/nomisdata/issues",
  "license": "https://spdx.org/licenses/MIT",
  "version": "0.1.1",
  "programmingLanguage": {
    "@type": "ComputerLanguage",
    "name": "R",
    "url": "https://r-project.org"
  },
  "runtimePlatform": "R version 4.4.1 (2024-06-14 ucrt)",
  "provider": {
    "@id": "https://cran.r-project.org",
    "@type": "Organization",
    "name": "Comprehensive R Archive Network (CRAN)",
    "url": "https://cran.r-project.org"
  },
  "author": [
    {
      "@type": "Person",
      "givenName": ["Cheryl", "Isabella"],
      "familyName": "Lim",
      "email": "cheryl.academic@gmail.com",
      "@id": "https://orcid.org/0009-0004-5766-1392"
    }
  ],
  "maintainer": [
    {
      "@type": "Person",
      "givenName": ["Cheryl", "Isabella"],
      "familyName": "Lim",
      "email": "cheryl.academic@gmail.com",
      "@id": "https://orcid.org/0009-0004-5766-1392"
    }
  ],
  "softwareSuggestions": [
    {
      "@type": "SoftwareApplication",
      "identifier": "cachem",
      "name": "cachem",
      "version": ">= 1.0.0",
      "provider": {
        "@id": "https://cran.r-project.org",
        "@type": "Organization",
        "name": "Comprehensive R Archive Network (CRAN)",
        "url": "https://cran.r-project.org"
      },
      "sameAs": "https://CRAN.R-project.org/package=cachem"
    },
    {
      "@type": "SoftwareApplication",
      "identifier": "ggplot2",
      "name": "ggplot2",
      "version": ">= 3.4.0",
      "provider": {
        "@id": "https://cran.r-project.org",
        "@type": "Organization",
        "name": "Comprehensive R Archive Network (CRAN)",
        "url": "https://cran.r-project.org"
      },
      "sameAs": "https://CRAN.R-project.org/package=ggplot2"
    },
    {
      "@type": "SoftwareApplication",
      "identifier": "janitor",
      "name": "janitor",
      "version": ">= 2.2.0",
      "provider": {
        "@id": "https://cran.r-project.org",
        "@type": "Organization",
        "name": "Comprehensive R Archive Network (CRAN)",
        "url": "https://cran.r-project.org"
      },
      "sameAs": "https://CRAN.R-project.org/package=janitor"
    },
    {
      "@type": "SoftwareApplication",
      "identifier": "knitr",
      "name": "knitr",
      "version": ">= 1.42",
      "provider": {
        "@id": "https://cran.r-project.org",
        "@type": "Organization",
        "name": "Comprehensive R Archive Network (CRAN)",
        "url": "https://cran.r-project.org"
      },
      "sameAs": "https://CRAN.R-project.org/package=knitr"
    },
    {
      "@type": "SoftwareApplication",
      "identifier": "memoise",
      "name": "memoise",
      "version": ">= 2.0.0",
      "provider": {
        "@id": "https://cran.r-project.org",
        "@type": "Organization",
        "name": "Comprehensive R Archive Network (CRAN)",
        "url": "https://cran.r-project.org"
      },
      "sameAs": "https://CRAN.R-project.org/package=memoise"
    },
    {
      "@type": "SoftwareApplication",
      "identifier": "rappdirs",
      "name": "rappdirs",
      "version": ">= 0.3.0",
      "provider": {
        "@id": "https://cran.r-project.org",
        "@type": "Organization",
        "name": "Comprehensive R Archive Network (CRAN)",
        "url": "https://cran.r-project.org"
      },
      "sameAs": "https://CRAN.R-project.org/package=rappdirs"
    },
    {
      "@type": "SoftwareApplication",
      "identifier": "readr",
      "name": "readr",
      "version": ">= 2.1.0",
      "provider": {
        "@id": "https://cran.r-project.org",
        "@type": "Organization",
        "name": "Comprehensive R Archive Network (CRAN)",
        "url": "https://cran.r-project.org"
      },
      "sameAs": "https://CRAN.R-project.org/package=readr"
    },
    {
      "@type": "SoftwareApplication",
      "identifier": "rmarkdown",
      "name": "rmarkdown",
      "version": ">= 2.20",
      "provider": {
        "@id": "https://cran.r-project.org",
        "@type": "Organization",
        "name": "Comprehensive R Archive Network (CRAN)",
        "url": "https://cran.r-project.org"
      },
      "sameAs": "https://CRAN.R-project.org/package=rmarkdown"
    },
    {
      "@type": "SoftwareApplication",
      "identifier": "rsdmx",
      "name": "rsdmx",
      "version": ">= 0.6.0",
      "provider": {
        "@id": "https://cran.r-project.org",
        "@type": "Organization",
        "name": "Comprehensive R Archive Network (CRAN)",
        "url": "https://cran.r-project.org"
      },
      "sameAs": "https://CRAN.R-project.org/package=rsdmx"
    },
    {
      "@type": "SoftwareApplication",
      "identifier": "scales",
      "name": "scales",
      "version": ">= 1.2.0",
      "provider": {
        "@id": "https://cran.r-project.org",
        "@type": "Organization",
        "name": "Comprehensive R Archive Network (CRAN)",
        "url": "https://cran.r-project.org"
      },
      "sameAs": "https://CRAN.R-project.org/package=scales"
    },
    {
      "@type": "SoftwareApplication",
      "identifier": "sf",
      "name": "sf",
      "version": ">= 1.0.0",
      "provider": {
        "@id": "https://cran.r-project.org",
        "@type": "Organization",
        "name": "Comprehensive R Archive Network (CRAN)",
        "url": "https://cran.r-project.org"
      },
      "sameAs": "https://CRAN.R-project.org/package=sf"
    },
    {
      "@type": "SoftwareApplication",
      "identifier": "testthat",
      "name": "testthat",
      "version": ">= 3.1.0",
      "provider": {
        "@id": "https://cran.r-project.org",
        "@type": "Organization",
        "name": "Comprehensive R Archive Network (CRAN)",
        "url": "https://cran.r-project.org"
      },
      "sameAs": "https://CRAN.R-project.org/package=testthat"
    },
    {
      "@type": "SoftwareApplication",
      "identifier": "withr",
      "name": "withr",
      "version": ">= 2.5.0",
      "provider": {
        "@id": "https://cran.r-project.org",
        "@type": "Organization",
        "name": "Comprehensive R Archive Network (CRAN)",
        "url": "https://cran.r-project.org"
      },
      "sameAs": "https://CRAN.R-project.org/package=withr"
    }
  ],
  "softwareRequirements": {
    "1": {
      "@type": "SoftwareApplication",
      "identifier": "cli",
      "name": "cli",
      "version": ">= 3.6.0",
      "provider": {
        "@id": "https://cran.r-project.org",
        "@type": "Organization",
        "name": "Comprehensive R Archive Network (CRAN)",
        "url": "https://cran.r-project.org"
      },
      "sameAs": "https://CRAN.R-project.org/package=cli"
    },
    "2": {
      "@type": "SoftwareApplication",
      "identifier": "dplyr",
      "name": "dplyr",
      "version": ">= 1.1.0",
      "provider": {
        "@id": "https://cran.r-project.org",
        "@type": "Organization",
        "name": "Comprehensive R Archive Network (CRAN)",
        "url": "https://cran.r-project.org"
      },
      "sameAs": "https://CRAN.R-project.org/package=dplyr"
    },
    "3": {
      "@type": "SoftwareApplication",
      "identifier": "httr2",
      "name": "httr2",
      "version": ">= 1.0.0",
      "provider": {
        "@id": "https://cran.r-project.org",
        "@type": "Organization",
        "name": "Comprehensive R Archive Network (CRAN)",
        "url": "https://cran.r-project.org"
      },
      "sameAs": "https://CRAN.R-project.org/package=httr2"
    },
    "4": {
      "@type": "SoftwareApplication",
      "identifier": "jsonlite",
      "name": "jsonlite",
      "version": ">= 1.8.0",
      "provider": {
        "@id": "https://cran.r-project.org",
        "@type": "Organization",
        "name": "Comprehensive R Archive Network (CRAN)",
        "url": "https://cran.r-project.org"
      },
      "sameAs": "https://CRAN.R-project.org/package=jsonlite"
    },
    "5": {
      "@type": "SoftwareApplication",
      "identifier": "rlang",
      "name": "rlang",
      "version": ">= 1.1.0",
      "provider": {
        "@id": "https://cran.r-project.org",
        "@type": "Organization",
        "name": "Comprehensive R Archive Network (CRAN)",
        "url": "https://cran.r-project.org"
      },
      "sameAs": "https://CRAN.R-project.org/package=rlang"
    },
    "6": {
      "@type": "SoftwareApplication",
      "identifier": "tibble",
      "name": "tibble",
      "version": ">= 3.2.0",
      "provider": {
        "@id": "https://cran.r-project.org",
        "@type": "Organization",
        "name": "Comprehensive R Archive Network (CRAN)",
        "url": "https://cran.r-project.org"
      },
      "sameAs": "https://CRAN.R-project.org/package=tibble"
    },
    "7": {
      "@type": "SoftwareApplication",
      "identifier": "utils",
      "name": "utils"
    },
    "8": {
      "@type": "SoftwareApplication",
      "identifier": "digest",
      "name": "digest",
      "provider": {
        "@id": "https://cran.r-project.org",
        "@type": "Organization",
        "name": "Comprehensive R Archive Network (CRAN)",
        "url": "https://cran.r-project.org"
      },
      "sameAs": "https://CRAN.R-project.org/package=digest"
    },
    "9": {
      "@type": "SoftwareApplication",
      "identifier": "methods",
      "name": "methods"
    },
    "10": {
      "@type": "SoftwareApplication",
      "identifier": "R",
      "name": "R",
      "version": ">= 4.1.0"
    },
    "SystemRequirements": null
  },
  "fileSize": "3003.079KB",
  "releaseNotes": "https://github.com/cherylisabella/nomisdata/blob/main/NEWS.md",
  "readme": "https://github.com/cherylisabella/nomisdata/blob/main/README.md",
  "contIntegration": "https://github.com/cherylisabella/nomisdata/actions/workflows/R-CMD-check.yaml",
  "developmentStatus": "https://lifecycle.r-lib.org/articles/stages.html#stable",
  "relatedLink": "https://CRAN.R-project.org/package=nomisdata"
}
